multiobjective_gbt/__init__.py
multiobjective_gbt/_base.py
multiobjective_gbt/_gb.py
multiobjective_gbt/_gb_losses.py
moo_gbt-0.0.5.dist-info/LICENSE
moo_gbt-0.0.5.dist-info/METADATA
moo_gbt-0.0.5.dist-info/WHEEL
moo_gbt-0.0.5.dist-info/top_level.txt
moo_gbt-0.0.5.dist-info/RECORD
