Metadata-Version: 2.1
Name: moo-gbt
Version: 0.0.5
Summary: Library for Multi-objective optimization in Gradient Boosted Trees
Home-page: https://github.com/Swiggy/Moo-GBT
Author: Shubha, Bhavi
Author-email: bhavi.chawla@swiggy.in
License: UNKNOWN
Project-URL: Bug Tracker, https://github.com/Swiggy/Moo-GBT/issues
Platform: UNKNOWN
Classifier: Programming Language :: Python :: 3
Classifier: License :: OSI Approved :: BSD License
Classifier: Operating System :: OS Independent
Requires-Python: >=3.6
License-File: LICENSE
